repo_to_md/__init__.py
repo_to_md/_core.py
repo_to_md/cli.py
repo_to_md-0.1.1.dist-info/METADATA
repo_to_md-0.1.1.dist-info/WHEEL
repo_to_md-0.1.1.dist-info/entry_points.txt
repo_to_md-0.1.1.dist-info/licenses/LICENSE
repo_to_md-0.1.1.dist-info/RECORD
