Metadata-Version: 2.4
Name: repo-to-md
Version: 0.1.1
Summary: Fetch git and GitHub repos as markdown for LLM and AI Agents context
Project-URL: Homepage, https://github.com/vduseev/repo-to-md
Project-URL: Repository, https://github.com/vduseev/repo-to-md
Project-URL: Issues, https://github.com/vduseev/repo-to-md/issues
Author-email: vduseev <vagiz@duseev.com>
Maintainer-email: vduseev <vagiz@duseev.com>
License-Expression: Apache-2.0
License-File: LICENSE
Keywords: ai,claude,context,fetch,git,llm,markdown,read,repo,repository,text
Classifier: Development Status :: 4 - Beta
Classifier: Intended Audience :: Developers
Classifier: License :: OSI Approved :: Apache Software License
Classifier: Programming Language :: Python :: 3
Classifier: Programming Language :: Python :: 3.10
Classifier: Programming Language :: Python :: 3.11
Classifier: Programming Language :: Python :: 3.12
Classifier: Programming Language :: Python :: 3.13
Classifier: Programming Language :: Python :: 3.14
Classifier: Programming Language :: Python :: 3.15
Classifier: Topic :: Software Development :: Libraries
Classifier: Topic :: Software Development :: Libraries :: Python Modules
Requires-Python: >=3.10
Requires-Dist: pathspec>=0.12.1
Requires-Dist: requests>=2.32.4
